five4_tools/__init__.py
five4_tools/buscarSeparador.py
five4_tools/datos.py
five4_tools/five4_utils.py
five4_tools/variables.py
five4_tools_andyvisco-0.3.dist-info/LICENCE.txt
five4_tools_andyvisco-0.3.dist-info/METADATA
five4_tools_andyvisco-0.3.dist-info/WHEEL
five4_tools_andyvisco-0.3.dist-info/top_level.txt
five4_tools_andyvisco-0.3.dist-info/RECORD
