Metadata-Version: 2.1
Name: five4-tools-andyvisco
Version: 0.3
Summary: Herramientas para entendimiento y modelado de datos
Home-page: https://github.com/Five4-Argentina/five4_tools
Author: Andres Visco
Author-email: andres.visco@five4.com.ar
License: UNKNOWN
Platform: UNKNOWN
Classifier: Programming Language :: Python :: 3.7
Classifier: License :: OSI Approved :: MIT License
Classifier: Operating System :: OS Independent
Requires-Python: >=3.7
Requires-Dist: Color-Console
Requires-Dist: pandas
